socomote/__init__.py
socomote/__main__.py
socomote/config.py
socomote/core.py
socomote/keys.py
socomote/station.py
socomote/tts_server.py
socomote/resources/example_config.yaml
socomote-0.1.0.dist-info/METADATA
socomote-0.1.0.dist-info/WHEEL
socomote-0.1.0.dist-info/top_level.txt
socomote-0.1.0.dist-info/RECORD
