Metadata-Version: 2.1
Name: socomote
Version: 0.1.0
Summary: Application for remote control of Sonos systems
Home-page: UNKNOWN
Author: Theo Dickson
Author-email: tmsdickson@gmail.com
License: MIT
Platform: UNKNOWN
Requires-Dist: pyyaml
Requires-Dist: soco (>=0.23.2)
Requires-Dist: getkey (>=0.6.5)
